crest/.DS_Store
crest/__init__.py
crest/config.py
crest/server.py
crest/__pycache__/__init__.cpython-38.pyc
crest/__pycache__/__init__.cpython-39.pyc
crest/__pycache__/config.cpython-37.pyc
crest/__pycache__/config.cpython-38.pyc
crest/__pycache__/config.cpython-39.pyc
crest/__pycache__/server.cpython-38.pyc
crest/__pycache__/server.cpython-39.pyc
crest/all_in_one/__init__.py
crest/all_in_one/crest_init.py
crest/all_in_one/__pycache__/__init__.cpython-38.pyc
crest/all_in_one/__pycache__/__init__.cpython-39.pyc
crest/all_in_one/__pycache__/crest_init.cpython-38.pyc
crest/all_in_one/__pycache__/crest_init.cpython-39.pyc
crest/all_in_one/__pycache__/crest_main.cpython-39.pyc
crest/operable/__init__.py
crest/operable/heading_analysis.py
crest/operable/__pycache__/__init__.cpython-38.pyc
crest/operable/__pycache__/__init__.cpython-39.pyc
crest/operable/__pycache__/heading_analysis.cpython-38.pyc
crest/operable/__pycache__/heading_analysis.cpython-39.pyc
crest/operable/__pycache__/ht_main.cpython-37.pyc
crest/operable/__pycache__/ht_main.cpython-38.pyc
crest/operable/__pycache__/ht_main.cpython-39.pyc
crest/operable/__pycache__/link_purpose.cpython-39.pyc
crest/perceivable/__init__.py
crest/perceivable/cc_transcript.py
crest/perceivable/keyboard_focus_indicator.py
crest/perceivable/__pycache__/__init__.cpython-38.pyc
crest/perceivable/__pycache__/__init__.cpython-39.pyc
crest/perceivable/__pycache__/cc_transcript.cpython-39.pyc
crest/perceivable/__pycache__/keyboard_focus_indicator.cpython-38.pyc
crest/perceivable/__pycache__/keyboard_focus_indicator.cpython-39.pyc
crest/perceivable/__pycache__/kfi_main.cpython-37.pyc
crest/perceivable/__pycache__/kfi_main.cpython-38.pyc
crest/perceivable/__pycache__/kfi_main.cpython-39.pyc
crest/utils/__init__.py
crest/utils/ads_domain.txt
crest/utils/get_common_function.py
crest/utils/startup_util.py
crest/utils/train_model.py
crest/utils/__pycache__/__init__.cpython-38.pyc
crest/utils/__pycache__/__init__.cpython-39.pyc
pythoncrest-1.0.0.dist-info/LICENSE
pythoncrest-1.0.0.dist-info/METADATA
pythoncrest-1.0.0.dist-info/WHEEL
pythoncrest-1.0.0.dist-info/top_level.txt
pythoncrest-1.0.0.dist-info/RECORD
