Metadata-Version: 2.1
Name: pythoncrest
Version: 1.0.0
Summary: Automated Accessibility Testing Tool
Home-page: https://vmware.github.io/crest
Author: Sheri Byrne Haber, Amit Garg, Joyce Oshita
Author-email: sbyrnehaber@vmware.com, gargam@vmware.com, ojoyce@vmware.com
License: MIT
Project-URL: Bug Tracker, https://github.com/vmware/crest/issues
Platform: UNKNOWN
Classifier: Topic :: Software Development :: Testing
Classifier: Programming Language :: Python :: 3
Classifier: License :: OSI Approved :: MIT License
Classifier: Operating System :: OS Independent
Requires-Python: >=3.6
Requires-Dist: selenium (>=3.141.0)
Requires-Dist: requests (>=2.24.0)
Requires-Dist: urllib3 (>=1.25.9)
Requires-Dist: webdriver-manager
Requires-Dist: pillow
Requires-Dist: pytesseract (>=0.3.6)
Requires-Dist: bs4 (>=0.0.1)
Requires-Dist: nltk (>=3.5)
Requires-Dist: transformers (>=4.5.0)
Requires-Dist: pandas (>=1.0.5)
Requires-Dist: numpy (>=1.19.0)
Requires-Dist: lxml (>=4.5.2)
Requires-Dist: flask (>=1.1.2)
Requires-Dist: flask-cors (>=3.0.10)
Requires-Dist: torch
